intelliscript/__init__.py
intelliscript/cli.py
intelliscript/py.typed
intelliscript/cli/__init__.py
intelliscript/cli/commands/__init__.py
intelliscript/cli/commands/extract_commands.py
intelliscript/core/__init__.py
intelliscript/core/config_manager.py
intelliscript/core/error_handler.py
intelliscript/core/intelliscript_main.py
intelliscript_ai-2.1.0.dist-info/METADATA
intelliscript_ai-2.1.0.dist-info/WHEEL
intelliscript_ai-2.1.0.dist-info/entry_points.txt
intelliscript_ai-2.1.0.dist-info/top_level.txt
intelliscript_ai-2.1.0.dist-info/RECORD
