Metadata-Version: 2.4
Name: intelliscript-ai
Version: 2.1.0
Summary: World's first AI CLI tool with Google LangExtract integration for command generation and data analysis
Home-page: https://github.com/hongping-zh/intelliscript
Author: IntelliScript Team
Author-email: IntelliScript Team <team@intelliscript.dev>
Project-URL: Homepage, https://github.com/hongping-zh/intelliscript
Project-URL: Documentation, https://github.com/hongping-zh/intelliscript/blob/main/README.md
Project-URL: Repository, https://github.com/hongping-zh/intelliscript.git
Project-URL: Bug Tracker, https://github.com/hongping-zh/intelliscript/issues
Project-URL: Feature Requests, https://github.com/hongping-zh/intelliscript/discussions
Project-URL: Changelog, https://github.com/hongping-zh/intelliscript/blob/main/CHANGELOG_v2.1.md
Keywords: ai,cli,command-line,langextract,data-extraction,visualization,automation,llm,openai,ollama,anthropic,google-gemini,data-analysis,reports
Classifier: Development Status :: 4 - Beta
Classifier: Intended Audience :: Developers
Classifier: Intended Audience :: System Administrators
Classifier: License :: OSI Approved :: MIT License
Classifier: Operating System :: OS Independent
Classifier: Programming Language :: Python :: 3
Classifier: Programming Language :: Python :: 3.8
Classifier: Programming Language :: Python :: 3.9
Classifier: Programming Language :: Python :: 3.10
Classifier: Programming Language :: Python :: 3.11
Classifier: Programming Language :: Python :: 3.12
Classifier: Topic :: Software Development :: Libraries :: Python Modules
Classifier: Topic :: System :: Systems Administration
Classifier: Topic :: Scientific/Engineering :: Artificial Intelligence
Classifier: Topic :: Text Processing :: Linguistic
Classifier: Topic :: Utilities
Classifier: Environment :: Console
Requires-Python: >=3.8
Requires-Dist: requests>=2.28.0
Requires-Dist: toml>=0.10.0
Requires-Dist: click>=8.0.0
Requires-Dist: rich>=13.4.0
Requires-Dist: langextract>=0.1.0
Requires-Dist: matplotlib>=3.7.0
Requires-Dist: seaborn>=0.12.0
Requires-Dist: plotly>=5.15.0
Requires-Dist: bokeh>=3.2.0
Requires-Dist: pandas>=2.0.0
Requires-Dist: numpy>=1.24.0
Requires-Dist: jinja2>=3.1.0
Requires-Dist: beautifulsoup4>=4.12.0
Requires-Dist: typer>=0.9.0
Requires-Dist: openpyxl>=3.1.0
Requires-Dist: pyyaml>=6.0
Requires-Dist: psutil>=5.9.0
Provides-Extra: ai-providers
Requires-Dist: openai>=1.0.0; extra == "ai-providers"
Requires-Dist: anthropic>=0.7.0; extra == "ai-providers"
Requires-Dist: google-generativeai>=0.3.0; extra == "ai-providers"
Provides-Extra: dev
Requires-Dist: pytest>=7.0.0; extra == "dev"
Requires-Dist: pytest-mock>=3.11.0; extra == "dev"
Requires-Dist: pytest-asyncio>=0.21.0; extra == "dev"
Requires-Dist: coverage[toml]>=7.2.0; extra == "dev"
Requires-Dist: black>=23.0.0; extra == "dev"
Requires-Dist: isort>=5.12.0; extra == "dev"
Requires-Dist: flake8>=6.0.0; extra == "dev"
Requires-Dist: mypy>=1.0.0; extra == "dev"
Requires-Dist: pre-commit>=3.0.0; extra == "dev"
Provides-Extra: docs
Requires-Dist: mkdocs>=1.4.0; extra == "docs"
Requires-Dist: mkdocs-material>=9.0.0; extra == "docs"
Requires-Dist: mkdocs-mermaid2-plugin>=0.6.0; extra == "docs"
Provides-Extra: all
Requires-Dist: intelliscript[ai-providers,dev,docs]; extra == "all"
Dynamic: author
Dynamic: home-page
Dynamic: requires-python
